strawgate_es_mcp/__init__.py
strawgate_es_mcp/main.py
strawgate_es_mcp/data_stream/summarize.py
strawgate_es_mcp/search/dsl.py
strawgate_es_mcp/search/esql.py
strawgate_es_mcp-0.6.0.dist-info/METADATA
strawgate_es_mcp-0.6.0.dist-info/WHEEL
strawgate_es_mcp-0.6.0.dist-info/entry_points.txt
strawgate_es_mcp-0.6.0.dist-info/RECORD
