Metadata-Version: 2.4
Name: strawgate_es_mcp
Version: 0.6.0
Summary: Strawgate's Elasticsearch MCP project
Requires-Python: >=3.12
Requires-Dist: aiohttp>=3.12.2
Requires-Dist: asyncclick>=8.1.8
Requires-Dist: elasticsearch<9.0.0,>=8.18.0
Requires-Dist: fastmcp<2.11.0
Requires-Dist: mcp>=1.9.0
Requires-Dist: pytest-asyncio>=1.0.0
Requires-Dist: python-dotenv>=1.1.0
